MANIFEST.in
README.md
setup.cfg
setup.py
admin_favorite/__init__.py
admin_favorite/admin.py
admin_favorite/apps.py
admin_favorite/models.py
admin_favorite/tests.py
admin_favorite/urls.py
admin_favorite/views.py
admin_favorite.egg-info/PKG-INFO
admin_favorite.egg-info/SOURCES.txt
admin_favorite.egg-info/dependency_links.txt
admin_favorite.egg-info/top_level.txt
admin_favorite/migrations/0001_initial.py
admin_favorite/migrations/__init__.py
admin_favorite/static/images/favorite.svg
admin_favorite/static/images/unfavorite.svg
admin_favorite/static/js/jquery.js
admin_favorite/templates/admin/app_list.html
admin_favorite/templates/admin/favorite_list.html
admin_favorite/templates/admin/index.html